devos/__init__.py
devos/cli.py
devos/commands/__init__.py
devos/commands/ai.py
devos/commands/ai_chat.py
devos/commands/ai_config.py
devos/commands/completion.py
devos/commands/config.py
devos/commands/env.py
devos/commands/groq.py
devos/commands/groq_chat.py
devos/commands/groq_enhanced.py
devos/commands/init.py
devos/commands/interactive.py
devos/commands/project.py
devos/commands/quick.py
devos/commands/quick_ai.py
devos/commands/report.py
devos/commands/ship.py
devos/commands/test.py
devos/commands/track.py
devos/core/__init__.py
devos/core/ai_config.py
devos/core/command_history.py
devos/core/completion.py
devos/core/config.py
devos/core/crypto.py
devos/core/database.py
devos/core/enhanced_errors.py
devos/core/exceptions.py
devos/core/progress.py
devos/core/rich_progress.py
devos/core/ai/__init__.py
devos/core/ai/cache.py
devos/core/ai/context.py
devos/core/ai/enhanced_context.py
devos/core/ai/error_handling.py
devos/core/ai/groq_provider.py
devos/core/ai/openai_provider.py
devos/core/ai/performance.py
devos/core/ai/provider.py
devos/core/ai/service.py
devos/core/export/markdown.py
devos_cli-0.1.0.dist-info/METADATA
devos_cli-0.1.0.dist-info/WHEEL
devos_cli-0.1.0.dist-info/entry_points.txt
devos_cli-0.1.0.dist-info/top_level.txt
devos_cli-0.1.0.dist-info/RECORD
